httpie_xsisip.py
httpie_xsisip-1.0.2.dist-info/METADATA
httpie_xsisip-1.0.2.dist-info/WHEEL
httpie_xsisip-1.0.2.dist-info/entry_points.txt
httpie_xsisip-1.0.2.dist-info/top_level.txt
httpie_xsisip-1.0.2.dist-info/RECORD
