Metadata-Version: 2.1
Name: httpie-xsisip
Version: 1.0.2
Summary: Broadsoft XSI SIP auth plugin for HTTPie.
Home-page: https://github.com/pbertera/httpie-xsisip
Author: Pietro Bertera
Author-email: pietro@bertera.it
License: BSD
Download-URL: https://github.com/pbertera/httpie-xsisip
Platform: UNKNOWN
Classifier: Development Status :: 5 - Production/Stable
Classifier: Programming Language :: Python
Classifier: Programming Language :: Python :: 2
Classifier: Programming Language :: Python :: 2.6
Classifier: Programming Language :: Python :: 2.7
Classifier: Programming Language :: Python :: 3
Classifier: Programming Language :: Python :: 3.3
Classifier: Programming Language :: Python :: 3.4
Classifier: Environment :: Plugins
Classifier: License :: OSI Approved :: BSD License
Classifier: Topic :: Internet :: WWW/HTTP
Classifier: Topic :: Utilities
Requires-Dist: httpie (>=0.7.0)
